LICENSE.txt
MANIFEST.in
README.md
requirements-dev.txt
requirements.txt
setup.cfg
setup.py
superlogica/__init__.py
superlogica/buider.py
superlogica/conn.py
superlogica/orquestrador.py
superlogica/sl_builder.py
superlogica/sl_conector.py
superlogica_conector.egg-info/PKG-INFO
superlogica_conector.egg-info/SOURCES.txt
superlogica_conector.egg-info/dependency_links.txt
superlogica_conector.egg-info/requires.txt
superlogica_conector.egg-info/top_level.txt
test/__init__.py
test/produtos_intake_test.py
test/test_authenticator.py