Metadata-Version: 2.1
Name: superlogica-conector
Version: 0.0.1
Summary: Data intake conector of API Superlogica for anywhere
Home-page: UNKNOWN
Author: crasdata
Author-email: anderson.santana@crasdata.com.br
License: MIT
Platform: UNKNOWN
Provides-Extra: dev
License-File: LICENSE.txt
